pyobiee/__init__.py
pyobiee/classes.py
pyobiee/functions.py
pyobiee-0.2.0.dist-info/LICENSE.txt
pyobiee-0.2.0.dist-info/METADATA
pyobiee-0.2.0.dist-info/WHEEL
pyobiee-0.2.0.dist-info/top_level.txt
pyobiee-0.2.0.dist-info/RECORD
