Metadata-Version: 2.1
Name: pyobiee
Version: 0.2.0
Summary: Python wrapper for OBIEE
Home-page: https://github.com/kazei92/pyobiee
Author: Timur Kazyev
Author-email: kazyev@me.com
Classifier: Programming Language :: Python :: 3
Classifier: License :: OSI Approved :: MIT License
Classifier: Operating System :: OS Independent
Requires-Python: >=3.5
License-File: LICENSE.txt
